expressmoney/db_router.py
expressmoney/decorators.py
expressmoney/exceptions.py
expressmoney/middleware.py
expressmoney/mixins.py
expressmoney/services.py
expressmoney/throttling.py
expressmoney/utils.py
expressmoney-0.5.0.dist-info/METADATA
expressmoney-0.5.0.dist-info/WHEEL
expressmoney-0.5.0.dist-info/top_level.txt
expressmoney-0.5.0.dist-info/RECORD
