Metadata-Version: 2.1
Name: expressmoney
Version: 0.5.0
Summary: SDK ExpressMoney
Home-page: https://github.com/zsergey85/
Author: Sergey Zherebtsov
Author-email: sergey@expressmoney.com
License: UNKNOWN
Download-URL: https://github.com/zsergey85/
Keywords: expressmoney
Platform: UNKNOWN
Classifier: Programming Language :: Python :: 3
Classifier: License :: OSI Approved :: MIT License
Classifier: Operating System :: OS Independent
Requires-Python: >=3.7
Requires-Dist: google-cloud-pubsub
Requires-Dist: google-cloud-tasks
Requires-Dist: google-cloud-storage
